eyeloc/__init__.py
eyeloc/center_estimation/__init__.py
eyeloc/center_estimation/darkestPixel.py
eyeloc/center_estimation/largestCompCentroid.py
eyeloc/filters/RANSAC.py
eyeloc/filters/__init__.py
eyeloc/filters/simpleFilters.py
eyeloc/fitting/__init__.py
eyeloc/fitting/circle.py
eyeloc/fitting/ellipse.py
eyeloc/localizers/__init__.py
eyeloc/localizers/daugman.py
eyeloc/localizers/hough.py
eyeloc/localizers/peaks.py
eyeloc/localizers/polar.py
eyeloc/localizers/utils.py
eyeloc/prepocessing/__init__.py
eyeloc/prepocessing/preprocessing.py
eyeloc/utils/__init__.py
eyeloc/utils/image/__init__.py
eyeloc/utils/image/read.py
eyeloc/utils/image/show.py
eyeloc-0.2.0.dist-info/licenses/LICENSE
eyeloc-0.2.0.dist-info/METADATA
eyeloc-0.2.0.dist-info/WHEEL
eyeloc-0.2.0.dist-info/top_level.txt
eyeloc-0.2.0.dist-info/RECORD
