Metadata-Version: 2.4
Name: eyeloc
Version: 0.2.0
Summary: Eye tracking and location detection system
Author-email: Max Proshkin <max.proshkin@mail.ru>
License-Expression: MIT
Project-URL: Repository, https://github.com/promaxV/eyeloc
Project-URL: Issues, https://github.com/promaxV/eyeloc/issues
Classifier: Development Status :: 3 - Alpha
Classifier: Intended Audience :: Developers
Classifier: Programming Language :: Python :: 3
Classifier: Programming Language :: Python :: 3.8
Classifier: Programming Language :: Python :: 3.9
Classifier: Programming Language :: Python :: 3.10
Classifier: Programming Language :: Python :: 3.11
Requires-Python: >=3.8
License-File: LICENSE
Requires-Dist: numpy
Requires-Dist: opencv-python
Requires-Dist: matplotlib
Requires-Dist: scipy
Dynamic: license-file
